logery/__init__.py
logery/cli.py
logery/config_logging.py
logery/filters.py
logery/formatters.py
logery/handlers.py
logery/settings.py
logery-0.0.2.dist-info/METADATA
logery-0.0.2.dist-info/WHEEL
logery-0.0.2.dist-info/entry_points.txt
logery-0.0.2.dist-info/top_level.txt
logery-0.0.2.dist-info/RECORD
