Metadata-Version: 2.4
Name: logery
Version: 0.0.2
Summary: A highly customizable logging library for Python.
Author-email: Miguel Tenório <deepydev42@gmail.com>
Project-URL: Homepage, https://github.com/pypa/sampleproject
Project-URL: Bug Tracker, https://github.com/pypa/sampleproject/issues
Classifier: Programming Language :: Python :: 3
Classifier: License :: OSI Approved :: MIT License
Classifier: Operating System :: OS Independent
Requires-Python: >=3.12
Requires-Dist: rich
Requires-Dist: python-dotenv
